```java
package com.atguigu.java;

import com.atguigu.java.chapter05.LocalVariablesTest;

import java.io.FileInputStream;
import java.io.FileNotFoundException;
import java.io.Serializable;
import java.sql.DriverManager;
import java.sql.SQLException;
import java.util.Date;

/**
 * @author codekiller
 * @date 2022/1/21 17:13
 * @Description TODO
 */
public class BytecodeFileTest extends Object implements Comparable<String>, Serializable {

    public int count = 0;

    public static int age = 1;  //没有ConstantValue，在类加载的准备阶段赋初值，初始化阶段赋值。
    public final int num = 5;  //有ConstantValue，但因为不是static，这项属性会被JVM忽略。实际上是在构造器里赋值的。
    public final int num_2;  //没有ConstantValue，在构造器里赋值。
    public static final int number = 2;  //有ConstantValue,static+final修饰的直接赋值String类型或者基本类型常量，JVM规范建议在初始化阶段赋值，但是HotSpot VM直接在准备阶段就赋值了(因此clinit方法中没有赋值代码)。
    public static final int number_2; //没有ConstantValue，static+final修饰的没有直接赋值String类型或者基本类型常量，在类加载的准备阶段赋初值，初始化阶段赋值。
    public static final ThreadLocal<Integer> o2 = new ThreadLocal<Integer>(); //没有ConstantValue，static+final修饰的其他引用类型常量，在类加载的准备阶段赋初值，初始化阶段赋值。


    public volatile int money = 100;

    static {
        age = 5;
        age_2 = 5;
        System.out.println(age);
        //        System.out.println(age_2);  //报错，非法的前向引用（static只能赋值，不能调用）
    }

    static {
        number_2 = 10;
        BytecodeFileTest.test3();
    }

    public static int age_2 = 10;

    public BytecodeFileTest(){
        this.age = 10;
        this.money = 20;
        this.count = 30;
        num_2 = 10;
    }

    public BytecodeFileTest(int age,int money){
        this.age = age;
        this.money = money;
        this.count = 30;
        num_2 = 10;
    }


    public static void main(String[] args) throws FileNotFoundException, SQLException {
        BytecodeFileTest test = new BytecodeFileTest();
        int num = 10;  //必须要初始化
        test.test2();

        test.sum(1,2);  //字节码中，返回后直接pop
        int sum = test.sum(3, 4);  //字节码中，返回后istore_3

        //异常表
        try {
            Thread.sleep(100);
        } catch (InterruptedException e) {
            e.printStackTrace();
        }
        try {
            Class.forName("com.mysql.jdbc.Driver");
        } catch (ClassNotFoundException e) {
            e.printStackTrace();
        }

        //异常属性
        new FileInputStream("");
        DriverManager.getConnection("","","");

    }



    public  String test1(Date dateP, String name2) {
        dateP = null;
        name2 = "miwuzonghuijie";
        double weight = 130.5;//占据两个slot
        char gender = '男';
        return dateP + name2;
    }

    public void test2() {
        this.count++;
    }

    public static void test3() {
        int a = 0;
        {
            int b = 0;
            b = a + 1;
        }
        //变量c使用之前已经销毁的变量b占据的slot的位置
        int c = a + 1;
    }

    public int sum(int a,int b){
        return a+b;
    }

    @Override
    public int compareTo(String o) {
        return 0;
    }

    class innerClass extends BytecodeFileTest implements Comparable<String>, Serializable{

    }
}

```



```java
"C:\Program Files\Java\jdk1.8.0_131\bin\javap.exe" -v com.atguigu.java.BytecodeFileTest
Classfile /D:/workspace/JVM/Code/target/classes/com/atguigu/java/BytecodeFileTest.class
  Last modified 2022-1-21; size 3347 bytes
  MD5 checksum 23dfdf8e70b0dcfc2828e1e0cf0959cb
  Compiled from "BytecodeFileTest.java"
//类型信息      
public class com.atguigu.java.BytecodeFileTest extends java.lang.Object implements java.lang.Comparable<java.lang.String>, java.io.Serializable
  minor version: 0
  major version: 52
  flags: ACC_PUBLIC, ACC_SUPER
//常量池，存储字面量和符号引用,它包含了 class 文件结构及其子结构中引用的所有字符串常量、类或接口名、字段名和其他常量。
//#1是符号地址
Constant pool: 
    #1 = Methodref          #40.#108      // java/lang/Object."<init>":()V
    #2 = Fieldref           #7.#109       // com/atguigu/java/BytecodeFileTest.count:I
    #3 = Fieldref           #7.#110       // com/atguigu/java/BytecodeFileTest.num:I
    #4 = Fieldref           #7.#111       // com/atguigu/java/BytecodeFileTest.money:I
    #5 = Fieldref           #7.#112       // com/atguigu/java/BytecodeFileTest.age:I
    #6 = Fieldref           #7.#113       // com/atguigu/java/BytecodeFileTest.num_2:I
    #7 = Class              #114          // com/atguigu/java/BytecodeFileTest
    #8 = Methodref          #7.#108       // com/atguigu/java/BytecodeFileTest."<init>":()V
    #9 = Methodref          #7.#115       // com/atguigu/java/BytecodeFileTest.test2:()V
   #10 = Long               100l
   #12 = Methodref          #116.#117     // java/lang/Thread.sleep:(J)V
   #13 = Class              #118          // java/lang/InterruptedException
   #14 = Methodref          #13.#119      // java/lang/InterruptedException.printStackTrace:()V
   #15 = String             #120          // com.mysql.jdbc.Driver
   #16 = Methodref          #121.#122     // java/lang/Class.forName:(Ljava/lang/String;)Ljava/lang/Class;
   #17 = Class              #123          // java/lang/ClassNotFoundException
   #18 = Methodref          #17.#119      // java/lang/ClassNotFoundException.printStackTrace:()V
   #19 = Class              #124          // java/io/FileInputStream
   #20 = String             #125          //
   #21 = Methodref          #19.#126      // java/io/FileInputStream."<init>":(Ljava/lang/String;)V
   #22 = Methodref          #127.#128     // java/sql/DriverManager.getConnection:(Ljava/lang/String;Ljava/lang/String;Ljava/lang/String;)Ljava/sql/Connection;
   #23 = String             #129          // miwuzonghuijie
   #24 = Double             130.5d
   #26 = Class              #130          // java/lang/StringBuilder
   #27 = Methodref          #26.#108      // java/lang/StringBuilder."<init>":()V
   #28 = Methodref          #26.#131      // java/lang/StringBuilder.append:(Ljava/lang/Object;)Ljava/lang/StringBuilder;
   #29 = Methodref          #26.#132      // java/lang/StringBuilder.append:(Ljava/lang/String;)Ljava/lang/StringBuilder;
   #30 = Methodref          #26.#133      // java/lang/StringBuilder.toString:()Ljava/lang/String;
   #31 = Class              #134          // java/lang/String
   #32 = Methodref          #7.#135       // com/atguigu/java/BytecodeFileTest.compareTo:(Ljava/lang/String;)I
   #33 = Class              #136          // java/lang/ThreadLocal
   #34 = Methodref          #33.#108      // java/lang/ThreadLocal."<init>":()V
   #35 = Fieldref           #7.#137       // com/atguigu/java/BytecodeFileTest.o2:Ljava/lang/ThreadLocal;
   #36 = Fieldref           #7.#138       // com/atguigu/java/BytecodeFileTest.age_2:I
   #37 = Fieldref           #139.#140     // java/lang/System.out:Ljava/io/PrintStream;
   #38 = Methodref          #141.#142     // java/io/PrintStream.println:(I)V
   #39 = Methodref          #7.#143       // com/atguigu/java/BytecodeFileTest.test3:()V
   #40 = Class              #144          // java/lang/Object
   #41 = Class              #145          // java/lang/Comparable
   #42 = Class              #146          // java/io/Serializable
   #43 = Class              #147          // com/atguigu/java/BytecodeFileTest$innerClass
   #44 = Utf8               innerClass
   #45 = Utf8               InnerClasses
   #46 = Utf8               count
   #47 = Utf8               I
   #48 = Utf8               age
   #49 = Utf8               num
   #50 = Utf8               ConstantValue
   #51 = Integer            5
   #52 = Utf8               num_2
   #53 = Utf8               number
   #54 = Integer            2
   #55 = Utf8               o2
   #56 = Utf8               Ljava/lang/ThreadLocal;
   #57 = Utf8               Signature
   #58 = Utf8               Ljava/lang/ThreadLocal<Ljava/lang/Integer;>;
   #59 = Utf8               money
   #60 = Utf8               age_2
   #61 = Utf8               <init>
   #62 = Utf8               ()V
   #63 = Utf8               Code
   #64 = Utf8               LineNumberTable
   #65 = Utf8               LocalVariableTable
   #66 = Utf8               this
   #67 = Utf8               Lcom/atguigu/java/BytecodeFileTest;
   #68 = Utf8               (II)V
   #69 = Utf8               main
   #70 = Utf8               ([Ljava/lang/String;)V
   #71 = Utf8               e
   #72 = Utf8               Ljava/lang/InterruptedException;
   #73 = Utf8               Ljava/lang/ClassNotFoundException;
   #74 = Utf8               args
   #75 = Utf8               [Ljava/lang/String;
   #76 = Utf8               test
   #77 = Utf8               StackMapTable
   #78 = Class              #75           // "[Ljava/lang/String;"
   #79 = Class              #114          // com/atguigu/java/BytecodeFileTest
   #80 = Class              #118          // java/lang/InterruptedException
   #81 = Class              #123          // java/lang/ClassNotFoundException
   #82 = Utf8               Exceptions
   #83 = Class              #148          // java/io/FileNotFoundException
   #84 = Class              #149          // java/sql/SQLException
   #85 = Utf8               test1
   #86 = Utf8               (Ljava/util/Date;Ljava/lang/String;)Ljava/lang/String;
   #87 = Utf8               dateP
   #88 = Utf8               Ljava/util/Date;
   #89 = Utf8               name2
   #90 = Utf8               Ljava/lang/String;
   #91 = Utf8               weight
   #92 = Utf8               D
   #93 = Utf8               gender
   #94 = Utf8               C
   #95 = Utf8               test2
   #96 = Utf8               test3
   #97 = Utf8               b
   #98 = Utf8               a
   #99 = Utf8               c
  #100 = Utf8               compareTo
  #101 = Utf8               (Ljava/lang/String;)I
  #102 = Utf8               o
  #103 = Utf8               (Ljava/lang/Object;)I
  #104 = Utf8               <clinit>
  #105 = Utf8               Ljava/lang/Object;Ljava/lang/Comparable<Ljava/lang/String;>;Ljava/io/Serializable;
  #106 = Utf8               SourceFile
  #107 = Utf8               BytecodeFileTest.java
  #108 = NameAndType        #61:#62       // "<init>":()V
  #109 = NameAndType        #46:#47       // count:I
  #110 = NameAndType        #49:#47       // num:I
  #111 = NameAndType        #59:#47       // money:I
  #112 = NameAndType        #48:#47       // age:I
  #113 = NameAndType        #52:#47       // num_2:I
  #114 = Utf8               com/atguigu/java/BytecodeFileTest
  #115 = NameAndType        #95:#62       // test2:()V
  #116 = Class              #150          // java/lang/Thread
  #117 = NameAndType        #151:#152     // sleep:(J)V
  #118 = Utf8               java/lang/InterruptedException
  #119 = NameAndType        #153:#62      // printStackTrace:()V
  #120 = Utf8               com.mysql.jdbc.Driver
  #121 = Class              #154          // java/lang/Class
  #122 = NameAndType        #155:#156     // forName:(Ljava/lang/String;)Ljava/lang/Class;
  #123 = Utf8               java/lang/ClassNotFoundException
  #124 = Utf8               java/io/FileInputStream
  #125 = Utf8
  #126 = NameAndType        #61:#157      // "<init>":(Ljava/lang/String;)V
  #127 = Class              #158          // java/sql/DriverManager
  #128 = NameAndType        #159:#160     // getConnection:(Ljava/lang/String;Ljava/lang/String;Ljava/lang/String;)Ljava/sql/Connection;
  #129 = Utf8               miwuzonghuijie
  #130 = Utf8               java/lang/StringBuilder
  #131 = NameAndType        #161:#162     // append:(Ljava/lang/Object;)Ljava/lang/StringBuilder;
  #132 = NameAndType        #161:#163     // append:(Ljava/lang/String;)Ljava/lang/StringBuilder;
  #133 = NameAndType        #164:#165     // toString:()Ljava/lang/String;
  #134 = Utf8               java/lang/String
  #135 = NameAndType        #100:#101     // compareTo:(Ljava/lang/String;)I
  #136 = Utf8               java/lang/ThreadLocal
  #137 = NameAndType        #55:#56       // o2:Ljava/lang/ThreadLocal;
  #138 = NameAndType        #60:#47       // age_2:I
  #139 = Class              #166          // java/lang/System
  #140 = NameAndType        #167:#168     // out:Ljava/io/PrintStream;
  #141 = Class              #169          // java/io/PrintStream
  #142 = NameAndType        #170:#171     // println:(I)V
  #143 = NameAndType        #96:#62       // test3:()V
  #144 = Utf8               java/lang/Object
  #145 = Utf8               java/lang/Comparable
  #146 = Utf8               java/io/Serializable
  #147 = Utf8               com/atguigu/java/BytecodeFileTest$innerClass
  #148 = Utf8               java/io/FileNotFoundException
  #149 = Utf8               java/sql/SQLException
  #150 = Utf8               java/lang/Thread
  #151 = Utf8               sleep
  #152 = Utf8               (J)V
  #153 = Utf8               printStackTrace
  #154 = Utf8               java/lang/Class
  #155 = Utf8               forName
  #156 = Utf8               (Ljava/lang/String;)Ljava/lang/Class;
  #157 = Utf8               (Ljava/lang/String;)V
  #158 = Utf8               java/sql/DriverManager
  #159 = Utf8               getConnection
  #160 = Utf8               (Ljava/lang/String;Ljava/lang/String;Ljava/lang/String;)Ljava/sql/Connection;
  #161 = Utf8               append
  #162 = Utf8               (Ljava/lang/Object;)Ljava/lang/StringBuilder;
  #163 = Utf8               (Ljava/lang/String;)Ljava/lang/StringBuilder;
  #164 = Utf8               toString
  #165 = Utf8               ()Ljava/lang/String;
  #166 = Utf8               java/lang/System
  #167 = Utf8               out
  #168 = Utf8               Ljava/io/PrintStream;
  #169 = Utf8               java/io/PrintStream
  #170 = Utf8               println
  #171 = Utf8               (I)V
{
  //字段信息
  public int count;
    descriptor: I
    flags: ACC_PUBLIC

  public static int age;
    descriptor: I
    flags: ACC_PUBLIC, ACC_STATIC

  
// ConstantValue属性的作用是通知虚拟机自动为静态变量赋值
//用final修饰不是在构造方法赋值(即直接赋值)的String类型或者基本类型成员变量，会带有ConstantValue属性。
//但只有被static关键字修饰的类变量才可以使用这项属性。       
  public final int num;
    descriptor: I
    flags: ACC_PUBLIC, ACC_FINAL
    ConstantValue: int 5

  public final int num_2;
    descriptor: I
    flags: ACC_PUBLIC, ACC_FINAL

  public static final int number;
    descriptor: I
    flags: ACC_PUBLIC, ACC_STATIC, ACC_FINAL
    ConstantValue: int 2
        
  public static final int number_2;
    descriptor: I
    flags: ACC_PUBLIC, ACC_STATIC, ACC_FINAL

  public static final java.lang.ThreadLocal<java.lang.Integer> o2;
    descriptor: Ljava/lang/ThreadLocal;
    flags: ACC_PUBLIC, ACC_STATIC, ACC_FINAL
    Signature: #58                          // Ljava/lang/ThreadLocal<Ljava/lang/Integer;>;

  public volatile int money;
    descriptor: I
    flags: ACC_PUBLIC, ACC_VOLATILE

  public static int age_2;
    descriptor: I
    flags: ACC_PUBLIC, ACC_STATIC

  //方法信息
  public com.atguigu.java.BytecodeFileTest();
    descriptor: ()V
    flags: ACC_PUBLIC
    Code:
      stack=2, locals=1, args_size=1
         0: aload_0
         1: invokespecial #1                  // Method java/lang/Object."<init>":()V
         4: aload_0
         5: iconst_0
         6: putfield      #2                  // Field count:I
         9: aload_0
        10: iconst_5
        11: putfield      #3                  // Field num:I
        14: aload_0
        15: bipush        100
        17: putfield      #4                  // Field money:I
        20: aload_0
        21: pop
        22: bipush        10
        24: putstatic     #5                  // Field age:I
        27: aload_0
        28: bipush        20
        30: putfield      #4                  // Field money:I
        33: aload_0
        34: bipush        30
        36: putfield      #2                  // Field count:I
        39: aload_0
        40: bipush        10
        42: putfield      #6                  // Field num_2:I
        45: return
      LineNumberTable:
        line 45: 0
        line 19: 4
        line 22: 9
        line 30: 14
        line 46: 20
        line 47: 27
        line 48: 33
        line 49: 39
        line 50: 45
      LocalVariableTable:
        Start  Length  Slot  Name   Signature
            0      46     0  this   Lcom/atguigu/java/BytecodeFileTest;

  public com.atguigu.java.BytecodeFileTest(int, int);
    descriptor: (II)V
    flags: ACC_PUBLIC
    Code:
      stack=2, locals=3, args_size=3
         0: aload_0
         1: invokespecial #1                  // Method java/lang/Object."<init>":()V
         4: aload_0
         5: iconst_0
         6: putfield      #2                  // Field count:I
         9: aload_0
        10: iconst_5
        11: putfield      #3                  // Field num:I
        14: aload_0
        15: bipush        100
        17: putfield      #4                  // Field money:I
        20: aload_0
        21: pop
        22: iload_1
        23: putstatic     #5                  // Field age:I
        26: aload_0
        27: iload_2
        28: putfield      #4                  // Field money:I
        31: aload_0
        32: bipush        30
        34: putfield      #2                  // Field count:I
        37: aload_0
        38: bipush        10
        40: putfield      #6                  // Field num_2:I
        43: return
      LineNumberTable:
        line 52: 0
        line 19: 4
        line 22: 9
        line 30: 14
        line 53: 20
        line 54: 26
        line 55: 31
        line 56: 37
        line 57: 43
      LocalVariableTable:
        Start  Length  Slot  Name   Signature
            0      44     0  this   Lcom/atguigu/java/BytecodeFileTest;
            0      44     1   age   I
            0      44     2 money   I

  public static void main(java.lang.String[]) throws java.io.FileNotFoundException, java.sql.SQLException;
    descriptor: ([Ljava/lang/String;)V
    flags: ACC_PUBLIC, ACC_STATIC
    Code:
      stack=3, locals=5, args_size=1
         0: new           #7                  // class com/atguigu/java/BytecodeFileTest
         3: dup
         4: invokespecial #8                  // Method "<init>":()V
         7: astore_1
         8: bipush        10
        10: istore_2
        11: aload_1
        12: invokevirtual #9                  // Method test2:()V
        15: aload_1
        16: iconst_1
        17: iconst_2
        18: invokevirtual #10                 // Method sum:(II)I
        21: pop
        22: aload_1
        23: iconst_3
        24: iconst_4
        25: invokevirtual #10                 // Method sum:(II)I
        28: istore_3
        29: ldc2_w        #11                 // long 100l
        32: invokestatic  #13                 // Method java/lang/Thread.sleep:(J)V
        35: goto          45
        38: astore        4
        40: aload         4
        42: invokevirtual #15                 // Method java/lang/InterruptedException.printStackTrace:()V
        45: ldc           #16                 // String com.mysql.jdbc.Driver
        47: invokestatic  #17                 // Method java/lang/Class.forName:(Ljava/lang/String;)Ljava/lang/Class;
        50: pop
        51: goto          61
        54: astore        4
        56: aload         4
        58: invokevirtual #19                 // Method java/lang/ClassNotFoundException.printStackTrace:()V
        61: new           #20                 // class java/io/FileInputStream
        64: dup
        65: ldc           #21                 // String
        67: invokespecial #22                 // Method java/io/FileInputStream."<init>":(Ljava/lang/String;)V
        70: pop
        71: ldc           #21                 // String
        73: ldc           #21                 // String
        75: ldc           #21                 // String
        77: invokestatic  #23                 // Method java/sql/DriverManager.getConnection:(Ljava/lang/String;Ljava/lang/String;Ljava/lang/String;)Ljava/sql/Connection;
        80: pop
        81: return
      Exception table:
         from    to  target type
            29    35    38   Class java/lang/InterruptedException
            45    51    54   Class java/lang/ClassNotFoundException
      LineNumberTable:
        line 63: 0
        line 64: 8
        line 65: 11
        line 66: 15
        line 67: 22
        line 72: 29
        line 75: 35
        line 73: 38
        line 74: 40
        line 77: 45
        line 80: 51
        line 78: 54
        line 79: 56
        line 83: 61
        line 84: 71
        line 86: 81
      LocalVariableTable:
        Start  Length  Slot  Name   Signature
           40       5     4     e   Ljava/lang/InterruptedException;
           56       5     4     e   Ljava/lang/ClassNotFoundException;
            0      82     0  args   [Ljava/lang/String;
            8      74     1  test   Lcom/atguigu/java/BytecodeFileTest;
           11      71     2   num   I
           29      53     3   sum   I
      StackMapTable: number_of_entries = 4
        frame_type = 255 /* full_frame */
          offset_delta = 38
          locals = [ class "[Ljava/lang/String;", class com/atguigu/java/BytecodeFileTest, int, int ]
          stack = [ class java/lang/InterruptedException ]
        frame_type = 6 /* same */
        frame_type = 72 /* same_locals_1_stack_item */
          stack = [ class java/lang/ClassNotFoundException ]
        frame_type = 6 /* same */
    Exceptions:
      throws java.io.FileNotFoundException, java.sql.SQLException

  public java.lang.String test1(java.util.Date, java.lang.String);
    descriptor: (Ljava/util/Date;Ljava/lang/String;)Ljava/lang/String;
    flags: ACC_PUBLIC
    Code:
      stack=2, locals=6, args_size=3
         0: aconst_null
         1: astore_1
         2: ldc           #23                 // String miwuzonghuijie
         4: astore_2
         5: ldc2_w        #24                 // double 130.5d
         8: dstore_3
         9: sipush        30007
        12: istore        5
        14: new           #26                 // class java/lang/StringBuilder
        17: dup
        18: invokespecial #27                 // Method java/lang/StringBuilder."<init>":()V
        21: aload_1
        22: invokevirtual #28                 // Method java/lang/StringBuilder.append:(Ljava/lang/Object;)Ljava/lang/StringBuilder;
        25: aload_2
        26: invokevirtual #29                 // Method java/lang/StringBuilder.append:(Ljava/lang/String;)Ljava/lang/StringBuilder;
        29: invokevirtual #30                 // Method java/lang/StringBuilder.toString:()Ljava/lang/String;
        32: areturn
      LineNumberTable:
        line 86: 0
        line 87: 2
        line 88: 5
        line 89: 9
        line 90: 14
      LocalVariableTable:
        Start  Length  Slot  Name   Signature
            0      33     0  this   Lcom/atguigu/java/BytecodeFileTest;
            0      33     1 dateP   Ljava/util/Date;
            0      33     2 name2   Ljava/lang/String;
            9      24     3 weight   D
           14      19     5 gender   C

  public void test2();
    descriptor: ()V
    flags: ACC_PUBLIC
    Code:
      stack=3, locals=1, args_size=1
         0: aload_0
         1: dup
         2: getfield      #2                  // Field count:I
         5: iconst_1
         6: iadd
         7: putfield      #2                  // Field count:I
        10: return
      LineNumberTable:
        line 94: 0
        line 95: 10
      LocalVariableTable:
        Start  Length  Slot  Name   Signature
            0      11     0  this   Lcom/atguigu/java/BytecodeFileTest;

  public static void test3();
    descriptor: ()V
    flags: ACC_PUBLIC, ACC_STATIC
    Code:
      stack=2, locals=2, args_size=0
         0: iconst_0
         1: istore_0
         2: iconst_0
         3: istore_1
         4: iload_0
         5: iconst_1
         6: iadd
         7: istore_1
         8: iload_0
         9: iconst_1
        10: iadd
        11: istore_1
        12: return
      LineNumberTable:
        line 98: 0
        line 100: 2
        line 101: 4
        line 104: 8
        line 105: 12
      LocalVariableTable:
        Start  Length  Slot  Name   Signature
            4       4     1     b   I
            2      11     0     a   I
           12       1     1     c   I
                                     
  public int sum(int, int);
    descriptor: (II)I
    flags: ACC_PUBLIC
    Code:
      stack=2, locals=3, args_size=3
         0: iload_1
         1: iload_2
         2: iadd
         3: ireturn
      LineNumberTable:
        line 113: 0
      LocalVariableTable:
        Start  Length  Slot  Name   Signature
            0       4     0  this   Lcom/atguigu/java/BytecodeFileTest;
            0       4     1     a   I
            0       4     2     b   I                                   

  public int compareTo(java.lang.String);
    descriptor: (Ljava/lang/String;)I
    flags: ACC_PUBLIC
    Code:
      stack=1, locals=2, args_size=2
         0: iconst_0
         1: ireturn
      LineNumberTable:
        line 109: 0
      LocalVariableTable:
        Start  Length  Slot  Name   Signature
            0       2     0  this   Lcom/atguigu/java/BytecodeFileTest;
            0       2     1     o   Ljava/lang/String;

  public int compareTo(java.lang.Object);
    descriptor: (Ljava/lang/Object;)I
    flags: ACC_PUBLIC, ACC_BRIDGE, ACC_SYNTHETIC
    Code:
      stack=2, locals=2, args_size=2
         0: aload_0
         1: aload_1
         2: checkcast     #31                 // class java/lang/String
         5: invokevirtual #32                 // Method compareTo:(Ljava/lang/String;)I
         8: ireturn
      LineNumberTable:
        line 17: 0
      LocalVariableTable:
        Start  Length  Slot  Name   Signature
            0       9     0  this   Lcom/atguigu/java/BytecodeFileTest;

  static {};
    descriptor: ()V
    flags: ACC_STATIC
    Code:
      stack=2, locals=0, args_size=0
         0: iconst_1
         1: putstatic     #5                  // Field age:I
         4: new           #33                 // class java/lang/ThreadLocal
         7: dup
         8: invokespecial #34                 // Method java/lang/ThreadLocal."<init>":()V
        11: putstatic     #35                 // Field o2:Ljava/lang/ThreadLocal;
        14: iconst_5
        15: putstatic     #5                  // Field age:I
        18: iconst_5
        19: putstatic     #36                 // Field age_2:I
        22: getstatic     #37                 // Field java/lang/System.out:Ljava/io/PrintStream;
        25: getstatic     #5                  // Field age:I
        28: invokevirtual #38                 // Method java/io/PrintStream.println:(I)V
        31: invokestatic  #39                 // Method test3:()V
        34: bipush        10
        36: putstatic     #36                 // Field age_2:I
        39: return
      LineNumberTable:
        line 21: 0
        line 25: 4
        line 33: 14
        line 34: 18
        line 35: 22
        line 40: 31
        line 43: 34
}
Signature: #105                         // Ljava/lang/Object;Ljava/lang/Comparable<Ljava/lang/String;>;Ljava/io/Serializable;
SourceFile: "BytecodeFileTest.java"
InnerClasses:
     #44= #43 of #7; //innerClass=class com/atguigu/java/BytecodeFileTest$innerClass of class com/atguigu/java/BytecodeFileTest

```



